build_bot/__init__.py
build_bot-1.3.data/scripts/build_bot
build_bot-1.3.dist-info/DESCRIPTION.rst
build_bot-1.3.dist-info/METADATA
build_bot-1.3.dist-info/RECORD
build_bot-1.3.dist-info/WHEEL
build_bot-1.3.dist-info/metadata.json
build_bot-1.3.dist-info/top_level.txt
