Metadata-Version: 2.0
Name: build-bot
Version: 1.3
Summary: A fast and easy way to manage CI builds
Home-page: https://github.com/davemachado/build-bot
Author: davemachado
Author-email: contact@davemachado.com
License: UNKNOWN
Download-URL: https://github.com/davemachado/build-bot/archive/1.0.tar.gz
Keywords: build,bot,github
Platform: UNKNOWN
